LeakagePro/Discovery.py
LeakagePro/LeakagePro.py
LeakagePro/LeakageProTypes.py
LeakagePro/__init__.py
LeakagePro/com/BaseCom.py
LeakagePro/com/SerialCom.py
LeakagePro/com/TCPCom.py
LeakagePro/com/__init__.py
leakagepro_com-0.0.7.dist-info/LICENSE
leakagepro_com-0.0.7.dist-info/METADATA
leakagepro_com-0.0.7.dist-info/WHEEL
leakagepro_com-0.0.7.dist-info/top_level.txt
leakagepro_com-0.0.7.dist-info/RECORD
