Metadata-Version: 2.1
Name: leakagepro-com
Version: 0.0.7
Summary: python bindings for leakagePro communication
Home-page: https://github.com/pieye/leakagePro-com
Author: Markus Proeller
Author-email: markus.proeller@pieye.org
License: GPLv3
Platform: UNKNOWN
Requires-Dist: pandas
Requires-Dist: zeroconf
Requires-Dist: pyserial
